setup.py
ggtracker/__init__.py
ggtracker/client.py
ggtracker_client.egg-info/PKG-INFO
ggtracker_client.egg-info/SOURCES.txt
ggtracker_client.egg-info/dependency_links.txt
ggtracker_client.egg-info/not-zip-safe
ggtracker_client.egg-info/requires.txt
ggtracker_client.egg-info/top_level.txt