Metadata-Version: 1.0
Name: ggtracker-client
Version: 0.1
Summary: API client for ggtracker.com
Home-page: http://github.com/tthieman/ggtracker-python
Author: Travis Thieman
Author-email: travis.thieman@gmail.com
License: BSD License
Platform: UNKNOWN
